Workbook
Name aporte: Planilha1!$D$18
Name patrimonio: Planilha1!$D$21
Name qtd_anos: Planilha1!$D$19
Name rendimento_carteira: Planilha1!$D$14
Name salario: Planilha1!$D$13
Name sugestao_investimento: Planilha1!$D$15
Name taxa_mensal: Planilha1!$D$20

Sheet Planilha1
B12: CONFIGURAÇÕES
B13: Salário | D13: 5000
B14: Rendimento Carteira | D14: 0.006
B15: Sugestão de Investimento (30%) | D15: =D13*30% -> 1500
B17: INVESTIMENTO MENSAL
B18: Quanto investir por mês? | D18: 1500
B19: Por quantos anos? | D19: 5
B20: Taxa de Rendimento mensal? | D20: 0.01079
B21: Patrimônio Acumulado? | D21: =FV(taxa_mensal,qtd_anos*12,aporte*-1) -> 125665.37
B22: Dividendos Mensais? | D22: =patrimonio*rendimento_carteira -> 753.99223
B24: CENÁRIOS | D24: DIVIDENDO
A25: 2 | B25: Quanto em 2 anos? | C25: =FV($D$20,$A25*12,$D$18*-1) -> 40841.441 | D25: =C25*rendimento_carteira -> 245.04865
A26: 5 | B26: Quanto em 5 anos? | C26: =FV($D$20,$A26*12,$D$18*-1) -> 125665.37 | D26: =C26*rendimento_carteira -> 753.99223
A27: 10 | B27: Quanto em 10 anos? | C27: =FV($D$20,$A27*12,$D$18*-1) -> 364926.32 | D27: =C27*rendimento_carteira -> 2189.5579
A28: 20 | B28: Quanto em 20 anos? | C28: =FV($D$20,$A28*12,$D$18*-1) -> 1687797.6 | D28: =C28*rendimento_carteira -> 10126.786
A29: 30 | B29: Quanto em 30 anos? | C29: =FV($D$20,$A29*12,$D$18*-1) -> 6483254.5 | D29: =C29*rendimento_carteira -> 38899.527
B31: PERFIL | C31: Agressivo
B32: VALOR A SER INVESTIDO POR MÊS | C32: =aporte -> 1500
B34: TIPO DE FII | C34: Percentual Sugerido | D34: Valores
B35: PAPEL | C35: =VLOOKUP($C$31&"-"&B35,'Tabela de Apoio'!$C:$F,4,0) -> 0.38 | D35: =C35*$C$32 -> 570
B36: TIJOLO | C36: =VLOOKUP($C$31&"-"&B36,'Tabela de Apoio'!$C:$F,4,0) -> 0.2 | D36: =C36*$C$32 -> 300
B37: HÍBRIDOS | C37: =VLOOKUP($C$31&"-"&B37,'Tabela de Apoio'!$C:$F,4,0) -> 0.05 | D37: =C37*$C$32 -> 75
B38: FOFS | C38: =VLOOKUP($C$31&"-"&B38,'Tabela de Apoio'!$C:$F,4,0) -> 0.1 | D38: =C38*$C$32 -> 150
B39: DESENVOLVIMENTO | C39: =VLOOKUP($C$31&"-"&B39,'Tabela de Apoio'!$C:$F,4,0) -> 0.17 | D39: =C39*$C$32 -> 255
B40: HOTELARIAS | C40: =VLOOKUP($C$31&"-"&B40,'Tabela de Apoio'!$C:$F,4,0) -> 0.1 | D40: =C40*$C$32 -> 150
D41: =SUM(D35:D40) -> 1500

Sheet Tabela de Apoio
C4: CHAVE COMPOSTA | D4: PERFIL | E4: TIPO DE FII | F4: % Sugerido
C5: =D5&"-"&E5 -> Conservador-PAPEL | D5: Conservador | E5: PAPEL | F5: 0.25
C6: =D6&"-"&E6 -> Conservador-TIJOLO | D6: Conservador | E6: TIJOLO | F6: 0.55
C7: =D7&"-"&E7 -> Conservador-HÍBRIDOS | D7: Conservador | E7: HÍBRIDOS | F7: 0.1
C8: =D8&"-"&E8 -> Conservador-FOFS | D8: Conservador | E8: FOFS | F8: 0.1
C9: =D9&"-"&E9 -> Conservador-DESENVOLVIMENTO | D9: Conservador | E9: DESENVOLVIMENTO | F9: 0
C10: =D10&"-"&E10 -> Conservador-HOTELARIAS | D10: Conservador | E10: HOTELARIAS | F10: 0
C11: =D11&"-"&E11 -> Moderado-PAPEL | D11: Moderado | E11: PAPEL | F11: 0.35
C12: =D12&"-"&E12 -> Moderado-TIJOLO | D12: Moderado | E12: TIJOLO | F12: 0.35
C13: =D13&"-"&E13 -> Moderado-HÍBRIDOS | D13: Moderado | E13: HÍBRIDOS | F13: 0.08
C14: =D14&"-"&E14 -> Moderado-FOFS | D14: Moderado | E14: FOFS | F14: 0.05
C15: =D15&"-"&E15 -> Moderado-DESENVOLVIMENTO | D15: Moderado | E15: DESENVOLVIMENTO | F15: 0.1
C16: =D16&"-"&E16 -> Moderado-HOTELARIAS | D16: Moderado | E16: HOTELARIAS | F16: 0.07
... C22: =D22&"-"&E22 -> Agressivo-HOTELARIAS | D22: Agressivo | E22: HOTELARIAS | F22: 0.1
